ApiValidations-1.0.0-py3.8-nspkg.pth
api/validations/__init__.py
api/validations/exceptions.py
api/validations/fields.py
api/validations/validate.py
ApiValidations-1.0.0.dist-info/METADATA
ApiValidations-1.0.0.dist-info/WHEEL
ApiValidations-1.0.0.dist-info/namespace_packages.txt
ApiValidations-1.0.0.dist-info/top_level.txt
ApiValidations-1.0.0.dist-info/RECORD
