Metadata-Version: 2.1
Name: ApiValidations
Version: 1.0.0
Summary: api-validation package.
Home-page: https://github.com/soni-vikas/easy-api-validation
Author: vikas
Author-email: x.vikassoni@gmail.com
License: UNKNOWN
Keywords: api
Platform: UNKNOWN
Classifier: Development Status :: 2 - Pre-Alpha
Classifier: Intended Audience :: Developers
Classifier: Natural Language :: English
Classifier: Programming Language :: Python :: 3
Classifier: Programming Language :: Python :: 3.4
Classifier: Programming Language :: Python :: 3.5
Classifier: Programming Language :: Python :: 3.6
Classifier: Programming Language :: Python :: 3.7
